power_of_10/__init__.py
power_of_10/athletes.py
power_of_10/coaches.py
power_of_10/exceptions.py
power_of_10/rankings.py
power_of_10/results.py
power_of_10-0.0.1.dist-info/LICENSE
power_of_10-0.0.1.dist-info/METADATA
power_of_10-0.0.1.dist-info/WHEEL
power_of_10-0.0.1.dist-info/top_level.txt
power_of_10-0.0.1.dist-info/RECORD
