Metadata-Version: 2.1
Name: power-of-10
Version: 0.0.1
Summary: A UK athletics API
Home-page: https://github.com/yasserqureshi1/power-of-10
Author: Yasser Qureshi
Author-email: yasser.m.q01@gmail.com
License: UNKNOWN
Project-URL: Bug Tracker, https://github.com/yasserqureshi1/power-of-10/issues
Platform: UNKNOWN
Classifier: Programming Language :: Python :: 3
Classifier: License :: OSI Approved :: MIT License
Classifier: Operating System :: OS Independent
Requires-Python: >=3.6
Requires-Dist: beautifulsoup4 (==4.9.3)
Requires-Dist: bs4 (==0.0.1)
Requires-Dist: certifi (==2020.12.5)
Requires-Dist: chardet (==4.0.0)
Requires-Dist: idna (==2.10)
Requires-Dist: numpy (==1.20.3)
Requires-Dist: requests (==2.25.1)
Requires-Dist: soupsieve (==2.2.1)
Requires-Dist: urllib3 (==1.26.4)
